quick_sci_plot/__init__.py
quick_sci_plot/functions.py
quick_sci_plot/__pycache__/__init__.cpython-36.pyc
quick_sci_plot/__pycache__/functions.cpython-36.pyc
quick_sci_plot-0.0.1.dist-info/LICENSE
quick_sci_plot-0.0.1.dist-info/METADATA
quick_sci_plot-0.0.1.dist-info/WHEEL
quick_sci_plot-0.0.1.dist-info/top_level.txt
quick_sci_plot-0.0.1.dist-info/RECORD
