Metadata-Version: 2.1
Name: quick-sci-plot
Version: 0.0.1
Summary: Quickly plot neat charts and figures for scientific publications
Home-page: http://github.com/dhchenx/quick-sci-plot
Author: Donghua Chen
Author-email: douglaschan@126.com
License: MIT
Project-URL: Bug Reports, https://github.com/dhchenx/quick-sci-plot/issues
Project-URL: Source, https://github.com/dhchenx/quick-sci-plot
Keywords: quick scientific plot
Platform: UNKNOWN
Classifier: Development Status :: 5 - Production/Stable
Classifier: Intended Audience :: Developers
Classifier: Topic :: Software Development :: Build Tools
Classifier: License :: OSI Approved :: MIT License
Classifier: Programming Language :: Python :: 3
Classifier: Programming Language :: Python :: 3.6
Classifier: Programming Language :: Python :: 3.7
Classifier: Programming Language :: Python :: 3.8
Classifier: Programming Language :: Python :: 3.9
Classifier: Programming Language :: Python :: 3 :: Only
Requires-Python: >=3.6, <4
License-File: LICENSE
Requires-Dist: pandas
Requires-Dist: quick-csv
Requires-Dist: matplotlib
Requires-Dist: seaborn
Provides-Extra: dev
Requires-Dist: check-manifest ; extra == 'dev'
Provides-Extra: test
Requires-Dist: coverage ; extra == 'test'
